MANIFEST.in
README.md
setup.py
Kreveik.egg-info/PKG-INFO
Kreveik.egg-info/SOURCES.txt
Kreveik.egg-info/dependency_links.txt
Kreveik.egg-info/requires.txt
Kreveik.egg-info/top_level.txt
kreveik/__init__.py
kreveik/classes/__init__.py
kreveik/classes/family.py
kreveik/classes/network.py
kreveik/classes/other.py
kreveik/family/__init__.py
kreveik/family/killer.py
kreveik/family/motifs.py
kreveik/genetic/__init__.py
kreveik/network/__init__.py
kreveik/network/generators.py
kreveik/network/motif.py
kreveik/network/mutators.py
kreveik/network/scorers.py
kreveik/network/selectors.py
kreveik/network/boolfuncs/__init__.py
kreveik/network/boolfuncs/boolfuncs.c
kreveik/network/boolfuncs/boolfuncs.py
kreveik/probes/__init__.py