Metadata-Version: 1.1
Name: Kreveik
Version: 0.6.0
Summary: Kreveik is a Python module for Boolean networks. With Kreveik, one can create, investigate dynamics of, form families of random Boolean networks.
Home-page: http://github.com/mehmetalianil/Kreveik/
Author: Mehmet Ali Anil
Author-email: mehmet.ali.anil@ieee.org
License: LICENSE.txt
Keywords: random boolean networks genetic algorithm
Platform: UNKNOWN
Classifier: Development Status :: 4 - Beta
Classifier: Environment :: Console
Classifier: Intended Audience :: Science/Research
Classifier: License :: Other/Proprietary License
Classifier: Natural Language :: English
Classifier: Operating System :: POSIX
Classifier: Programming Language :: Python :: 2.7
Classifier: Programming Language :: C
Classifier: Topic :: Scientific/Engineering :: Bio-Informatics
Classifier: Topic :: Scientific/Engineering :: Information Analysis
Classifier: Topic :: Scientific/Engineering :: Physics
